MANIFEST.in
setup.py
incuna_feincms.egg-info/PKG-INFO
incuna_feincms.egg-info/SOURCES.txt
incuna_feincms.egg-info/dependency_links.txt
incuna_feincms.egg-info/top_level.txt
incunafein/__init__.py
incunafein/models.py
incunafein/admin/__init__.py
incunafein/admin/editor.py
incunafein/admin/filterspecs.py
incunafein/admin/tree_editor.py
incunafein/content/__init__.py
incunafein/content/medialibrary/__init__.py
incunafein/content/medialibrary/models.py
incunafein/content/paypal/__init__.py
incunafein/content/paypal/models.py
incunafein/content/video/__init__.py
incunafein/content/video/models.py
incunafein/content/videosection/__init__.py
incunafein/content/videosection/models.py
incunafein/fixtures/incunafein_navigation_data.json
incunafein/management/__init__.py
incunafein/management/commands/__init__.py
incunafein/management/commands/import_medialibrary.py
incunafein/module/__init__.py
incunafein/module/medialibrarychapters/__init__.py
incunafein/module/medialibrarychapters/models.py
incunafein/module/medialibrarychapters/extensions/__init__.py
incunafein/module/medialibrarychapters/extensions/chapters.py
incunafein/module/navigation/__init__.py
incunafein/module/navigation/admin.py
incunafein/module/navigation/models.py
incunafein/module/navigation/tests.py
incunafein/module/navigation/views.py
incunafein/module/navigation/templates/navigation/navitem.html
incunafein/module/navigation/templatetags/__init__.py
incunafein/module/navigation/templatetags/navigationtags.py
incunafein/module/page/__init__.py
incunafein/module/page/search_indexes.py
incunafein/module/page/extensions/__init__.py
incunafein/module/page/extensions/article_categories.py
incunafein/module/page/extensions/articles.py
incunafein/module/page/extensions/comments.py
incunafein/module/page/extensions/links.py
incunafein/module/page/extensions/mediafiles.py
incunafein/module/page/extensions/prepared_date.py
incunafein/module/page/extensions/show_title.py
incunafein/templates/content/videocontent/default.html
incunafein/templates/content/videosection/default.html
incunafein/templates/incunafein/page/mediafiles.html
