Metadata-Version: 1.0
Name: incuna-feincms
Version: 1.0.0
Summary: Provides enhancements to FeinCMS.
Home-page: http://incuna.com/
Author: Incuna Ltd
Author-email: admin@incuna.com
License: UNKNOWN
Platform: UNKNOWN
